reg_decoder.v
module reg_decoder(reg_code, enable);
  input [2:0] reg_code; // either the register to put onto the bus, or to be loaded into
  output reg [4:0] enable; 

  always @(*) begin 
    case (reg_code) // reg_code comes from fsm 
      3'b000:  enable = 5'b00001; // r0 is either being loaded to or put on the bus
      3'b001:  enable = 5'b00010; // r1 same 
      3'b010:  enable = 5'b00100; // r2 and so on ...
      3'b011:  enable = 5'b01000; // g
      3'b100:  enable = 5'b10000; // a
      default: enable = 5'b00000; 
    endcase
  end
endmodule

bus_reg.v
module bus_reg (load, out, in, clk, rst);
  input [15:0] in;
  input load, clk, rst;
  output reg [15:0] out;

  always @(posedge clk or posedge rst) begin
    if (rst) begin
      out <= 16'h0000;
    end
      else if (load) begin
      out <= in;
    end
  end
endmodule

alu.v
module alu (reg_in, bus_in, out, add_or_sub);
  input [15:0] reg_in, bus_in;
  input add_or_sub;
  output reg [15:0] out;

  always @(*) begin
    if (add_or_sub == 1'b0)
      out = reg_in + bus_in;
    else
      out = reg_in - bus_in;
  end
endmodule

fsm.v
module fsm (instruction, clk, rst, load_reg, drive_reg, add_or_sub, immediate, imm_enable);
  input [15:0] instruction;
  input clk, rst;
  output reg [2:0] load_reg, drive_reg;
  output reg [15:0] immediate;
  output reg add_or_sub, imm_enable;

  reg [3:0] cur_state; 
  reg [3:0] next_state;
  reg [2:0] ldi_reg_code; 
  
  always @(posedge clk or posedge rst) begin
    
    if (rst) begin
      cur_state <= 4'b0000;
      ldi_reg_code <= 3'b000;
    end 
    
    else begin
      cur_state <= next_state;

      if (cur_state == 4'b0000 && instruction[15:12] == 4'b0000) begin
        ldi_reg_code <= instruction[11:10];
      end

    end
    
  end

  always @(*) begin
    // defaults 
    load_reg = 3'b111;
    drive_reg = 3'b111;
    add_or_sub = 0;
    imm_enable = 0;
    immediate = 16'b0;
    next_state = cur_state; 

    case (cur_state) // based on the instruction, we choose which operation to complete
      4'b0000: begin // Decoding
        case (instruction[15:12])
          4'b0000 : next_state = 4'b0001; // LDI
          4'b0001 : next_state = 4'b0011; // MOV
          4'b0010 : next_state = 4'b0100; // ADD
          4'b0011 : next_state = 4'b0111; // SUB
          default : next_state = 4'b0000;
        endcase
      end
      
      // LDI 1 
      4'b0001 : next_state = 4'b0010; 

      // LDI 2
      4'b0010 : begin 
        drive_reg = 3'b101; // immediate onto bus
        load_reg = ldi_reg_code; // loading immediate to that ldi_reg_code
        imm_enable = 1; // we are taking a constant value not a register
        immediate = instruction; // constant value to be loaded is the instruction 
        next_state = 4'b0000;
      end

      // MOV
      4'b0011 : begin
        load_reg = instruction[11:10]; // load to destination register
        drive_reg = instruction[9:8]; // register onto bus
        next_state = 4'b0000;
      end

      // ADD 1
      4'b0100 : begin
        drive_reg = instruction[11:10]; // destination register onto bus
        load_reg = 3'b100; // load to A
        next_state = 4'b0101; 
      end

      // ADD 2
      4'b0101 : begin
        drive_reg = instruction[9:8]; // register onto bus
        load_reg = 3'b011; // load to G
        add_or_sub = 0; 
        next_state = 4'b0110;
      end

      // ADD 3 
      4'b0110 : begin
        drive_reg = 3'b011; // G onto bus         
        load_reg = instruction[11:10]; // load to destination register
        next_state = 4'b0000;          
      end

      // SUB 1
      4'b0111: begin
        drive_reg = instruction[11:10]; // destination register onto bus
        load_reg = 3'b100; // load to A
        next_state = 4'b1000; 
      end

      // SUB 2
      4'b1000 : begin
        drive_reg = instruction[9:8]; // register onto bus
        load_reg = 3'b011; // load to G 
        add_or_sub = 1; // subtract operation
        next_state = 4'b1001;
      end

      // SUB 3 
      4'b1001 : begin
        drive_reg = 3'b011; // G onto bus      
        load_reg = instruction[11:10]; // load to destination register
        next_state = 4'b0000;
      end

      default : next_state = 4'b0000;

      // after an operation is complete we return to state 0, awaiting next instruciton
    endcase
  end
endmodule

controller.v
module controller (instruction, clk, rst);
  input [15:0] instruction;
  input clk, rst;

  reg [15:0] bus; 
  wire [4:0] drive, load;
  wire [2:0] drive_reg_code, load_reg_code;
  wire [15:0] a_to_alu, alu_to_g, immediate;
  wire add_or_sub, imm_enable;
  wire [15:0] r0_out, r1_out, r2_out, g_out;

  fsm control_unit (
    .instruction(instruction),.clk(clk),.rst(rst),
    .load_reg(load_reg_code),.drive_reg(drive_reg_code),
    .add_or_sub(add_or_sub),.immediate(immediate),.imm_enable(imm_enable)
  );

  alu logic_unit (
    .reg_in(a_to_alu),.bus_in(bus), 
    .out(alu_to_g),.add_or_sub(add_or_sub)
  );

  bus_reg r0 (.load(load[0]),.out(r0_out),.in(bus),.clk(clk),.rst(rst));
  bus_reg r1 (.load(load[1]),.out(r1_out),.in(bus),.clk(clk),.rst(rst));
  bus_reg r2 (.load(load[2]),.out(r2_out),.in(bus),.clk(clk),.rst(rst));
  bus_reg g  (.load(load[3]),.out(g_out),.in(alu_to_g),.clk(clk),.rst(rst));
  bus_reg a  (.load(load[4]),.out(a_to_alu),.in(bus),.clk(clk),.rst(rst));

  reg_decoder load_dec (.reg_code(load_reg_code),.enable(load));
  reg_decoder drive_dec (.reg_code(drive_reg_code),.enable(drive));

  always @(*) begin // allows only one register to drive the bus at a time
    case (drive_reg_code) // prevents a contention over bus driving
      3'b000:  bus = r0_out;
      3'b001:  bus = r1_out;
      3'b010:  bus = r2_out;
      3'b011:  bus = g_out;
      3'b101:  bus = immediate; 
      default: bus = 16'h0000;
    endcase
  end
endmodule

essentials_tb.v
`timescale 1ns/1ps 

module essentials_tb; 
    reg [15:0] instructionSignal; 
    reg clockSignal; 
    reg resetSignal; 

    controller dut (
        .instruction(instructionSignal),
        .clk(clockSignal),
        .rst(resetSignal)
    ); 

    always begin
        #5;
        clockSignal = ~clockSignal; 
    end

    initial begin 
        $monitor("Time:%0t | Instr:%h | Bus:%h | State:%b | R0:%h | R1:%h | R2:%h", 
                $time, instructionSignal, dut.bus, dut.control_unit.cur_state, 
                dut.r0_out, dut.r1_out, dut.r2_out);
        
        $dumpfile("essentials_tb.vcd"); 
        $dumpvars(0, essentials_tb); 

        clockSignal = 0; 
        resetSignal = 1; 
        instructionSignal = 16'h0000;
        
        // initial pause to get rid of xxxx
        @(negedge clockSignal);
        @(negedge clockSignal);
        @(negedge clockSignal); 
        resetSignal = 0; 

        // using hex for simplicity
        // load 15 into register 0 (LDI) takes 3 cycles to execute
        instructionSignal = 16'h0000; // ldi r0
        @(negedge clockSignal);     
        instructionSignal = 16'h000F; // 15
        @(negedge clockSignal); 
        @(negedge clockSignal); 

        // load 10 into register 1 (LDI) takes 3 cycles to execute
        instructionSignal = 16'h0400; // ldi r1
        @(negedge clockSignal); 
        instructionSignal = 16'h000A; // 10 
        @(negedge clockSignal); 
        @(negedge clockSignal); 

        // register 0 += register 1 (ADD) takes 4 cycles to execute
        instructionSignal = 16'h2100; 
        @(negedge clockSignal);
        @(negedge clockSignal);
        @(negedge clockSignal);
        @(negedge clockSignal); 

        // register 0 -= register 1 (SUB) takes 4 cycles to execute
        instructionSignal = 16'h3100; 
        @(negedge clockSignal);
        @(negedge clockSignal);
        @(negedge clockSignal);
        @(negedge clockSignal);

        // register 2 = register 0 (MOV) takes 2 cycles to execute
        instructionSignal = 16'h1800; 
        @(negedge clockSignal);
        @(negedge clockSignal); 

        // clears teh bus
        instructionSignal = 16'h0000;

        #20 $finish;
    end

endmodule

// compile
// iverilog -o essentials alu.v bus_reg.v controller.v fsm.v reg_decoder.v essentials_tb.v

//run
// vvp essentials

essentials_tb.vcd
$date
	Mon May 18 18:23:47 2026
$end
$version
	Icarus Verilog
$end
$timescale
	1ps
$end
$scope module essentials_tb $end
$var reg 1 ! clockSignal $end
$var reg 16 " instructionSignal [15:0] $end
$var reg 1 # resetSignal $end
$scope module dut $end
$var wire 1 ! clk $end
$var wire 16 $ instruction [15:0] $end
$var wire 1 # rst $end
$var wire 16 % r2_out [15:0] $end
$var wire 16 & r1_out [15:0] $end
$var wire 16 ' r0_out [15:0] $end
$var wire 3 ( load_reg_code [2:0] $end
$var wire 5 ) load [4:0] $end
$var wire 16 * immediate [15:0] $end
$var wire 1 + imm_enable $end
$var wire 16 , g_out [15:0] $end
$var wire 3 - drive_reg_code [2:0] $end
$var wire 5 . drive [4:0] $end
$var wire 16 / alu_to_g [15:0] $end
$var wire 1 0 add_or_sub $end
$var wire 16 1 a_to_alu [15:0] $end
$var reg 16 2 bus [15:0] $end
$scope module a $end
$var wire 1 ! clk $end
$var wire 16 3 in [15:0] $end
$var wire 1 4 load $end
$var wire 1 # rst $end
$var reg 16 5 out [15:0] $end
$upscope $end
$scope module control_unit $end
$var wire 1 ! clk $end
$var wire 16 6 instruction [15:0] $end
$var wire 1 # rst $end
$var reg 1 0 add_or_sub $end
$var reg 4 7 cur_state [3:0] $end
$var reg 3 8 drive_reg [2:0] $end
$var reg 1 + imm_enable $end
$var reg 16 9 immediate [15:0] $end
$var reg 3 : ldi_reg_code [2:0] $end
$var reg 3 ; load_reg [2:0] $end
$var reg 4 < next_state [3:0] $end
$upscope $end
$scope module drive_dec $end
$var wire 3 = reg_code [2:0] $end
$var reg 5 > enable [4:0] $end
$upscope $end
$scope module g $end
$var wire 1 ! clk $end
$var wire 1 ? load $end
$var wire 1 # rst $end
$var wire 16 @ in [15:0] $end
$var reg 16 A out [15:0] $end
$upscope $end
$scope module load_dec $end
$var wire 3 B reg_code [2:0] $end
$var reg 5 C enable [4:0] $end
$upscope $end
$scope module logic_unit $end
$var wire 1 0 add_or_sub $end
$var wire 16 D bus_in [15:0] $end
$var wire 16 E reg_in [15:0] $end
$var reg 16 F out [15:0] $end
$upscope $end
$scope module r0 $end
$var wire 1 ! clk $end
$var wire 16 G in [15:0] $end
$var wire 1 H load $end
$var wire 1 # rst $end
$var reg 16 I out [15:0] $end
$upscope $end
$scope module r1 $end
$var wire 1 ! clk $end
$var wire 16 J in [15:0] $end
$var wire 1 K load $end
$var wire 1 # rst $end
$var reg 16 L out [15:0] $end
$upscope $end
$scope module r2 $end
$var wire 1 ! clk $end
$var wire 16 M in [15:0] $end
$var wire 1 N load $end
$var wire 1 # rst $end
$var reg 16 O out [15:0] $end
$upscope $end
$upscope $end
$upscope $end
$enddefinitions $end
$comment Show the parameter values. $end
$dumpall
$end
#0
$dumpvars
b0 O
0N
b0 M
b0 L
0K
b0 J
b0 I
0H
b0 G
b0 F
b0 E
b0 D
b0 C
b111 B
b0 A
b0 @
0?
b0 >
b111 =
b1 <
b111 ;
b0 :
b0 9
b111 8
b0 7
b0 6
b0 5
04
b0 3
b0 2
b0 1
00
b0 /
b0 .
b111 -
b0 ,
0+
b0 *
b0 )
b111 (
b0 '
b0 &
b0 %
b0 $
1#
b0 "
0!
$end
#5000
1!
#10000
0!
#15000
1!
#20000
0!
#25000
1!
#30000
0#
0!
#35000
b10 <
b1 7
1!
#40000
b10 <
b1111 "
b1111 $
b1111 6
0!
#45000
1H
b1111 /
b1111 @
b1111 F
b1 )
b1 C
b1111 2
b1111 3
b1111 D
b1111 G
b1111 J
b1111 M
b0 <
b1111 *
b1111 9
1+
b0 (
b0 ;
b0 B
b101 -
b101 8
b101 =
b10 7
1!
#50000
0!
#55000
b0 /
b0 @
b0 F
0H
b0 2
b0 3
b0 D
b0 G
b0 J
b0 M
b0 )
b0 C
b1 <
b0 *
b0 9
0+
b111 -
b111 8
b111 =
b111 (
b111 ;
b111 B
b0 7
b1111 '
b1111 I
1!
#60000
b1 <
b10000000000 "
b10000000000 $
b10000000000 6
0!
#65000
b10 <
b1 :
b1 7
1!
#70000
b10 <
b1010 "
b1010 $
b1010 6
0!
#75000
1K
b1010 /
b1010 @
b1010 F
b10 )
b10 C
b1010 2
b1010 3
b1010 D
b1010 G
b1010 J
b1010 M
b0 <
b1010 *
b1010 9
1+
b1 (
b1 ;
b1 B
b101 -
b101 8
b101 =
b10 7
1!
#80000
0!
#85000
0K
b0 /
b0 @
b0 F
b0 )
b0 C
b0 2
b0 3
b0 D
b0 G
b0 J
b0 M
b1 <
b0 *
b0 9
0+
b111 -
b111 8
b111 =
b111 (
b111 ;
b111 B
b1010 &
b1010 L
b0 7
1!
#90000
b100 <
b10000100000000 "
b10000100000000 $
b10000100000000 6
0!
#95000
14
b1111 /
b1111 @
b1111 F
b10000 )
b10000 C
b1 .
b1 >
b1111 2
b1111 3
b1111 D
b1111 G
b1111 J
b1111 M
b101 <
b100 (
b100 ;
b100 B
b0 -
b0 8
b0 =
b100 7
1!
#100000
0!
#105000
04
1?
b10 .
b10 >
b1010 2
b1010 3
b1010 D
b1010 G
b1010 J
b1010 M
b1000 )
b1000 C
b11001 /
b11001 @
b11001 F
b110 <
b1 -
b1 8
b1 =
b11 (
b11 ;
b11 B
b1111 1
b1111 5
b1111 E
b101 7
1!
#110000
0!
#115000
b101000 /
b101000 @
b101000 F
0?
1H
b1000 .
b1000 >
b11001 2
b11001 3
b11001 D
b11001 G
b11001 J
b11001 M
b1 )
b1 C
b0 <
b11 -
b11 8
b11 =
b0 (
b0 ;
b0 B
b110 7
b11001 ,
b11001 A
1!
#120000
0!
#125000
0H
b1111 /
b1111 @
b1111 F
b0 .
b0 >
b0 )
b0 C
b0 2
b0 3
b0 D
b0 G
b0 J
b0 M
b100 <
b111 -
b111 8
b111 =
b111 (
b111 ;
b111 B
b11001 '
b11001 I
b0 7
1!
#130000
b111 <
b11000100000000 "
b11000100000000 $
b11000100000000 6
0!
#135000
14
b101000 /
b101000 @
b101000 F
b10000 )
b10000 C
b1 .
b1 >
b11001 2
b11001 3
b11001 D
b11001 G
b11001 J
b11001 M
b1000 <
b100 (
b100 ;
b100 B
b0 -
b0 8
b0 =
b111 7
1!
#140000
0!
#145000
04
1?
b10 .
b10 >
b1010 2
b1010 3
b1010 D
b1010 G
b1010 J
b1010 M
b1000 )
b1000 C
b1111 /
b1111 @
b1111 F
b1001 <
10
b1 -
b1 8
b1 =
b11 (
b11 ;
b11 B
b11001 1
b11001 5
b11001 E
b1000 7
1!
#150000
0!
#155000
0?
1H
b101000 /
b101000 @
b101000 F
b1000 .
b1000 >
b1111 2
b1111 3
b1111 D
b1111 G
b1111 J
b1111 M
b1 )
b1 C
b0 <
00
b11 -
b11 8
b11 =
b0 (
b0 ;
b0 B
b1001 7
b1111 ,
b1111 A
1!
#160000
0!
#165000
0H
b11001 /
b11001 @
b11001 F
b0 .
b0 >
b0 )
b0 C
b0 2
b0 3
b0 D
b0 G
b0 J
b0 M
b111 <
b111 -
b111 8
b111 =
b111 (
b111 ;
b111 B
b1111 '
b1111 I
b0 7
1!
#170000
b11 <
b1100000000000 "
b1100000000000 $
b1100000000000 6
0!
#175000
b101000 /
b101000 @
b101000 F
1N
b1 .
b1 >
b1111 2
b1111 3
b1111 D
b1111 G
b1111 J
b1111 M
b100 )
b100 C
b0 <
b0 -
b0 8
b0 =
b10 (
b10 ;
b10 B
b11 7
1!
#180000
0!
#185000
0N
b11001 /
b11001 @
b11001 F
b0 .
b0 >
b0 )
b0 C
b0 2
b0 3
b0 D
b0 G
b0 J
b0 M
b11 <
b111 -
b111 8
b111 =
b111 (
b111 ;
b111 B
b1111 %
b1111 O
b0 7
1!
#190000
b1 <
b0 "
b0 $
b0 6
0!
#195000
b10 <
b0 :
b1 7
1!
#200000
0!
#205000
1H
b1 )
b1 C
b0 <
1+
b0 (
b0 ;
b0 B
b101 -
b101 8
b101 =
b10 7
1!
